fastpluggy_plugin/tasks_worker/__init__.py
fastpluggy_plugin/tasks_worker/config.py
fastpluggy_plugin/tasks_worker/metrics.py
fastpluggy_plugin/tasks_worker/plugin.py
fastpluggy_plugin/tasks_worker/broker/README_RABBITMQ.md
fastpluggy_plugin/tasks_worker/broker/__init__.py
fastpluggy_plugin/tasks_worker/broker/contracts.py
fastpluggy_plugin/tasks_worker/broker/factory.py
fastpluggy_plugin/tasks_worker/broker/local.py
fastpluggy_plugin/tasks_worker/broker/memory.py
fastpluggy_plugin/tasks_worker/broker/postgres.py
fastpluggy_plugin/tasks_worker/broker/rabbitmq.py
fastpluggy_plugin/tasks_worker/celery_compat/__init__.py
fastpluggy_plugin/tasks_worker/celery_compat/beat_capture.py
fastpluggy_plugin/tasks_worker/celery_compat/discovery.py
fastpluggy_plugin/tasks_worker/celery_compat/dummy.py
fastpluggy_plugin/tasks_worker/celery_compat/router.py
fastpluggy_plugin/tasks_worker/core/__init__.py
fastpluggy_plugin/tasks_worker/core/base_heartbeat.py
fastpluggy_plugin/tasks_worker/core/context.py
fastpluggy_plugin/tasks_worker/core/events.py
fastpluggy_plugin/tasks_worker/core/executor.py
fastpluggy_plugin/tasks_worker/core/executor_manager.py
fastpluggy_plugin/tasks_worker/core/log_handler.py
fastpluggy_plugin/tasks_worker/core/runner.py
fastpluggy_plugin/tasks_worker/core/status.py
fastpluggy_plugin/tasks_worker/core/topic.py
fastpluggy_plugin/tasks_worker/core/utils.py
fastpluggy_plugin/tasks_worker/persistence/__init__.py
fastpluggy_plugin/tasks_worker/persistence/models/__init__.py
fastpluggy_plugin/tasks_worker/persistence/models/context.py
fastpluggy_plugin/tasks_worker/persistence/models/report.py
fastpluggy_plugin/tasks_worker/persistence/models/scheduled.py
fastpluggy_plugin/tasks_worker/persistence/repository/__init__.py
fastpluggy_plugin/tasks_worker/persistence/repository/context.py
fastpluggy_plugin/tasks_worker/persistence/repository/report.py
fastpluggy_plugin/tasks_worker/persistence/repository/schedule_monitoring.py
fastpluggy_tasks_worker-0.3.244.dist-info/METADATA
fastpluggy_tasks_worker-0.3.244.dist-info/WHEEL
fastpluggy_tasks_worker-0.3.244.dist-info/entry_points.txt
fastpluggy_tasks_worker-0.3.244.dist-info/top_level.txt
fastpluggy_tasks_worker-0.3.244.dist-info/RECORD
