Metadata-Version: 2.4
Name: fastpluggy-tasks-worker
Version: 0.3.244
Summary: Task Runner plugin for Fastpluggy
Author: FastPluggy Team
Requires-Python: >=3.8
Requires-Dist: croniter
Requires-Dist: psutil
Requires-Dist: python-dateutil>=2.9.0
Requires-Dist: prometheus-client
Requires-Dist: fastpluggy-crud-tools>=0.2.12
Requires-Dist: fastpluggy>=0.3.42
Provides-Extra: rabbitmq
Requires-Dist: pika>=1.3.0; extra == "rabbitmq"
Provides-Extra: postgres
Requires-Dist: SQLAlchemy>=2.0; extra == "postgres"
Requires-Dist: psycopg[binary]>=3.1; extra == "postgres"
Provides-Extra: dev
Requires-Dist: pytest>=7.0; extra == "dev"
Requires-Dist: pytest-cov>=4.0; extra == "dev"
Requires-Dist: pytest-asyncio>=0.21; extra == "dev"
Requires-Dist: testcontainers[postgres,rabbitmq]>=4.0.0; extra == "dev"
